sense_data/__init__.py
sense_data/client.py
sense_data/decorator.py
sense_data/dictobj.py
sense_data/stock_pb2.py
sense_data/stock_pb2_grpc.py
sense_data-0.7.0.dist-info/METADATA
sense_data-0.7.0.dist-info/WHEEL
sense_data-0.7.0.dist-info/top_level.txt
sense_data-0.7.0.dist-info/RECORD
